{
    "menu": [
        {
            "e": "Bratwurst mit Kartoffelpüree und Gemüse (1,5,G)",
            "d": "Zitronenpudding (2,6,G)",
            "ev": "Vegetarische Bratwurst mit Kartoffelpürree und Gemüse (1,3,4,F,G)",
            "dv": "Zitronenpudding (2,6,G)"
        },
        {
            "e": "Putenstreifen mit Früchte-Currysoße und Reis (6)",
            "d": "Joghurt mit Himbeeren (G)",
            "ev": "Gemüsereispfanne",
            "dv": "Joghurt mit Himbeeren (G)"
        },
        {
            "e": "Tortelloni mit Ricotta gefüllt in Sahnesoße mit Gemüse (A,C,G)",
            "d": "Tiramisu (6,G)",
            "ev": "Tortelloni mit Ricotta gefüllt in Sahnesoße mit Gemüse (A,C,G)",
            "dv": "Tiramisu (6,G)"
        },
        {
            "e": "Paniertes Putenschnitzel mit Herzoginkartoffeln und Erbsen-Karottengemüse (A,C,G)",
            "d": "Erdbeermilch (G)",
            "ev": "Gemüseschnitzel mit Herzoginkartoffeln (A,C,G)",
            "dv": "Erdbeermilch (G)"
        },
        {
            "e": "Foodsaver: Lieblingsgerichte der Woche (A,C,D,G,H,I,J)",
            "d": "Dessert",
            "ev": "Thunfischsteak mit Kartoffeln und Gemüse (D)",
            "dv": "Dessert"
        }
    ],
    "last_update": 1749776453
}